{
  "type_of_establishment": "bar-restaurante",
  "place_name": "Beirut",
  "property_type": "particular",
  "address": {
      "establishment_phone_number": "78315883",
      "district": "Plaza",
      "location": "Calle 1ra entre A y B, Vedado",
      "coordinates": null
  },
  "schedules": {
      "monday": {
          "open": "11:00",
          "closed": "23:00"
      },
      "tuesday": {
          "open": "11:00",
          "closed": "23:00"
      },
      "wednesday": {
          "open": "11:00",
          "closed": "23:00"
      },
      "thursday": {
          "open": "11:00",
          "closed": "23:00"
      },
      "friday": {
          "open": "11:00",
          "closed": "23:00"
      },
      "saturday": {
          "open": "11:00",
          "closed": "23:00"
      },
      "sunday": {
          "open": "11:00",
          "closed": "23:00"
      }
  },
  "location_details": {
      "rating": {
          "google": {
              "stars": null,
              "number_of_reviews": null
          },
          "tripadvisor": {
              "stars": null,
              "number_of_reviews": null
          },
          "facebook": {
              "stars": null,
              "number_of_reviews": null
          }
      },
      "establishment_capacity": "grande",
      "decoration": "contemporanea",
      "festive_decorations": false,
      "home_uniform": "casual",
      "collaboration_for_events": false,
      "type_of_concurrent_clients": [
          "familias",
          "amistades"
      ],
      "energy_backup": false
  },
  "services": {
      "social_networks": {
          "web_page": [
              false,
              {
                  "url": null
              }
          ],
          "facebook": [
              false,
              {
                  "url": null
              }
          ],
          "instagram": [
              false,
              {
                  "url": null
              }
          ],
          "whatsapp": "50956929"
      },
      "child_care": false,
      "disable_support": false,
      "parking": true,
      "delivery": true,
      "reserves": true,
      "rent_from_the_client": false,
      "vip_zone": false,
      "pet_friendly": false
  },
  "pay_meth": {
      "cash": true,
      "transfer": {
          "transfermovil": true,
          "visa": false,
          "mastercard": false
      },
      "currency": {
          "cup": true,
          "usd": false,
          "euro": false,
          "mlc": false
      },
      "10% charge": false
  },
  "menu_details": {
    "kind_of_food": [
      "oriental"
    ],
    "menu_card": {
      "menu_sections": {
        "main_courses": [
          {
            "courses": [
              {
                "name": "Shish Taouk",
                "price": 2950
              },
              {
                "name": "Kabab",
                "price": 2900
              },
              {
                "name": "Shish Taouk-Kabab",
                "price": 2800
              },
              {
                "name": "Shish Kabab",
                "price": 2000
              },
              {
                "name": "Tajin",
                "price": 3500
              },
              {
                "name": "Mixto Beirut",
                "price": 3700
              }
            ]
          }
        ],
        "breads": [
          {
            "courses": [
              {
                "name": " Shawarma de pollo",
                "price": 1520
              },
              {
                "name": " Shawarma árabe",
                "price": 1520
              },
              {
                "name": "Sandwich Falafel",
                "price": 1420
              },
              {
                "name": " Sandwich Shish Taouk",
                "price": 1720
              },
              {
                "name": " Sandwich Kabab",
                "price": 1720
              }
            ]
          }
        ],
        "rations": [
          {
            "name": "Fetuche",
            "price": 1500
          },
          {
            "name": "Ensalada mixta",
            "price": 2000
          },
          {
            "name": "Betabel",
            "price": 2000
          },
          {
            "name": "Ensalada Beirut",
            "price": 2100
          },
          {
            "name": "Tabule",
            "price": 3000
          }
        ],
        "desserts": [
          {
            "courses": [
              {
                "name": "Sensei borracho",
                "price": 1920
              },
              {
                "name": "Maestro Shifu",
                "price": 2080
              },
              {
                "name": "Mei Mei",
                "price": 1800
              },
              {
                "name": "Maestro Shinobi",
                "price": 1760
              }
            ]
          }
        ],
        "liquids": [
          {
            "alcoholic_beverages": [
              {
                "beers": [
                  {
                    "name": "Cervezas",
                    "price": 390
                  }
                ]
              }
            ],
            "natual_juices": [
              {
                "name": "Limonada",
                "price": 410
              },
              {
                "name": "Jugos naturales",
                "price": 410
              }
            ],
            "water": [
              {
                "name": "Agua nacional",
                "price": 175
              }
            ],
            "soft_drinks": [
              {
                "name": "Refrescos importados",
                "price": 290
              },
              {
                "name": "Maltas",
                "price": 290
              }
            ],
            "coffees": [
              {
                "name": "Expresso",
                "price": 125
              },
              {
                "name": "Capuccino",
                "price": 300
              },
              {
                "name": "Americano",
                "price": 160
              },
              {
                "name": "Cortado",
                "price": 200
              },
              {
                "name": "Te",
                "price": 150
              }
            ]
          }
        ]
      }
    }
  }
}