{
  "type_of_establishment": "bar",
  "place_name": "Mini Bar (Hotel Royalton Paseo Del Prado)",
  "property_type": "particular",
  "address": {
      "establishment_phone_number": null,
      "district": "Habana Vieja",
      "location": "Prado y Malecón",
      "coordinates": "23.14556061167238, -82.3584210674671"
  },
  "schedules": {
      "monday": {
          "open": "00:00",
          "closed": "24:00"
      },
      "tuesday": {
          "open": "00:00",
          "closed": "24:00"
      },
      "wednesday": {
          "open": "00:00",
          "closed": "24:00"
      },
      "thursday": {
          "open": "00:00",
          "closed": "24:00"
      },
      "friday": {
          "open": "00:00",
          "closed": "24:00"
      },
      "saturday": {
          "open": "00:00",
          "closed": "24:00"
      },
      "sunday": {
          "open": "00:00",
          "closed": "24:00"
      }
  },
  "location_details": {
      "rating": {
          "google": {
              "stars": 4.2,
              "number_of_reviews": 305
          },
          "tripadvisor": {
              "stars": null,
              "number_of_reviews": null
          },
          "facebook": {
              "stars": 4.8,
              "number_of_reviews": 15
          }
      },
      "establishment_capacity": "grande",
      "decoration": "moderna",
      "festive_decorations": true,
      "home_uniform": "casual",
      "collaboration_for_events": true,
      "type_of_concurrent_clients": [
          "parejas",
          "amistades",
          "familias"
      ],
      "energy_backup": true
  },
  "services": {
      "social_networks": {
          "web_page": [
              true,
              {
                  "url": "https://www.royaltonresorts.com/resorts/habana/dining-drinks/restaurants"
              }
          ],
          "facebook": [
              true,
              {
                  "url": "https://www.facebook.com/RoyaltonHabana/?locale=es_LA"
              }
          ],
          "instagram": [
              true,
              {
                  "url": "https://www.instagram.com/royaltonhabana/?hl=es"
              }
          ],
          "whatsapp": null
      },
      "child_care": false,
      "disable_support": false,
      "parking": false,
      "delivery": false,
      "reserves": false,
      "rent_from_the_client": false,
      "vip_zone": false,
      "pet_friendly": false
  },
  "pay_meth": {
      "cash": true,
      "transfer": {
          "transfermovil": true,
          "visa": true,
          "mastercard": true
      },
      "currency": {
          "cup": true,
          "usd": true,
          "euro": true,
          "mlc": true
      },
      "10% charge": true
  },
  "menu_details": {
    "kind_of_food": [
      "bebidas"
    ],
    "menu_card": {
      "menu_sections": {
        "liquids": [
          {
            "alcoholic_beverages": [
              {
                "beers": [
                  {
                    "name": "Cerveza nacional / National beer",
                    "price": 600
                  },
                  {
                    "name": "Cerveza importada / Imported beer",
                    "price": 750
                  }
                ],
                "shots": [
                  {
                    "name": "Ron en miniatura (45ml) / Miniature rum (45ml)",
                    "price": 850
                  }
                ]
              }
            ],
            "natual_juices": [
              {
                "name": "Jugo de frutas / Fruit juice",
                "price": 360
              }
            ],
            "soft_drinks": [
              {
                "name": "Refresco / Soda",
                "price": 390
              }
            ],
            "water": [
              {
                "name": "Agua tónica / Tonic water",
                "price": 450
              },
              {
                "name": "Agua natural / Natural water",
                "price": 600
              },
              {
                "name": "Agua gaseada / Sparkling water",
                "price": 600
              }
            ]
          }
        ]
      }
    }
  }
}